tumiaji/__init__.py
tumiaji/require.py
tumiaji/sambura.py
tumiaji-0.0.1.dist-info/METADATA
tumiaji-0.0.1.dist-info/WHEEL
tumiaji-0.0.1.dist-info/top_level.txt
tumiaji-0.0.1.dist-info/RECORD
