Metadata-Version: 2.1
Name: tumiaji
Version: 0.0.1
Summary: fun functions and classes to do boring coders tasks easily
Home-page: UNKNOWN
Author: Maryimana
Author-email: <tombutoyi@gmail.com>
License: UNKNOWN
Platform: UNKNOWN
Classifier: Development Status :: 1 - Planning
Classifier: Intended Audience :: Developers
Classifier: Programming Language :: Python :: 3
Classifier: Operating System :: Unix
Classifier: Operating System :: MacOS :: MacOS X
Classifier: Operating System :: Microsoft :: Windows
